chikovani_sample/__init__.py
chikovani_sample-0.0.1.dist-info/METADATA
chikovani_sample-0.0.1.dist-info/WHEEL
chikovani_sample-0.0.1.dist-info/RECORD
